overloadlib/__init__.py
overloadlib/__main__.py
overloadlib/overloadlib.py
overloadlib/py.typed
overloadlib-0.3.0.dist-info/entry_points.txt
overloadlib-0.3.0.dist-info/LICENSE.rst
overloadlib-0.3.0.dist-info/WHEEL
overloadlib-0.3.0.dist-info/METADATA
overloadlib-0.3.0.dist-info/RECORD
