Metadata-Version: 2.1
Name: overloadlib
Version: 0.3.0
Summary: A python package to implement overloading of functions in python.
Home-page: https://github.com/NicDom/overloadlib
License: MIT
Keywords: python
Author: Niclas D. Gesing
Author-email: nicdomgesing@gmail.com
Requires-Python: >=3.7.1,<4.0.0
Classifier: Development Status :: 5 - Production/Stable
Classifier: Intended Audience :: Developers
Classifier: License :: OSI Approved :: MIT License
Classifier: Operating System :: OS Independent
Classifier: Programming Language :: Python :: 3
Classifier: Programming Language :: Python :: 3.10
Classifier: Programming Language :: Python :: 3.7
Classifier: Programming Language :: Python :: 3.8
Classifier: Programming Language :: Python :: 3.9
Classifier: Topic :: Software Development :: Libraries :: Python Modules
Requires-Dist: importlib_metadata (>=4.5.0,<5.0.0); python_version < "3.8"
Project-URL: Changelog, https://github.com/NicDom/overloadlib/releases
Project-URL: Documentation, https://overloadlib.readthedocs.io
Project-URL: Repository, https://github.com/NicDom/overloadlib
